boundless_aiogram/__init__.py
boundless_aiogram/cli.py
boundless_aiogram-1.0.7.dist-info/METADATA
boundless_aiogram-1.0.7.dist-info/WHEEL
boundless_aiogram-1.0.7.dist-info/entry_points.txt
boundless_aiogram-1.0.7.dist-info/top_level.txt
boundless_aiogram-1.0.7.dist-info/RECORD
