Metadata-Version: 2.4
Name: boundless-aiogram
Version: 1.0.7
Summary: A modern, production-ready framework for building scalable Telegram bots with Aiogram 3.x
Home-page: https://github.com/MythicalCosmic/boundless-aiogram
Author: MythicalCosmic
Author-email: qodirjonov0854@gmail.com
License: MIT
Project-URL: Bug Tracker, https://github.com/MythicalCosmic/boundless-aiogram/issues
Project-URL: Documentation, https://github.com/MythicalCosmic/boundless-aiogram/wiki
Classifier: Development Status :: 4 - Beta
Classifier: Intended Audience :: Developers
Classifier: License :: OSI Approved :: MIT License
Classifier: Programming Language :: Python :: 3
Classifier: Programming Language :: Python :: 3.8
Classifier: Programming Language :: Python :: 3.9
Classifier: Programming Language :: Python :: 3.10
Classifier: Programming Language :: Python :: 3.11
Classifier: Programming Language :: Python :: 3.12
Classifier: Topic :: Software Development :: Libraries :: Application Frameworks
Classifier: Topic :: Communications :: Chat
Classifier: Framework :: AsyncIO
Requires-Python: >=3.8
Requires-Dist: aiogram>=3.0.0
Requires-Dist: alembic>=1.7
Requires-Dist: pyyaml
Requires-Dist: sqlalchemy>=2.0
Requires-Dist: python-dotenv>=1.0.0
Requires-Dist: aiosqlite
Dynamic: author
Dynamic: author-email
Dynamic: classifier
Dynamic: description
Dynamic: description-content-type
Dynamic: home-page
Dynamic: license
Dynamic: project-url
Dynamic: requires-dist
Dynamic: requires-python
Dynamic: summary
